hp/__init__.py
hp/params.py
hp/parser.py
tests/__init__.py
tests/test_params.py
hp-0.0.3.dist-info/METADATA
hp-0.0.3.dist-info/WHEEL
hp-0.0.3.dist-info/top_level.txt
hp-0.0.3.dist-info/RECORD
