Metadata-Version: 2.1
Name: hp
Version: 0.0.3
Summary: Hyperparameters
Home-page: https://github.com/michalwols/hp
Author: Michal Wolski
Author-email: michalwols@gmail.com
License: MIT
Platform: UNKNOWN
Requires-Python: >=3.7
